LICENSE.rst
README.rst
baked.py
setup.py
baked.egg-info/PKG-INFO
baked.egg-info/SOURCES.txt
baked.egg-info/dependency_links.txt
baked.egg-info/entry_points.txt
baked.egg-info/not-zip-safe
baked.egg-info/top_level.txt