Metadata-Version: 1.1
Name: baked
Version: 0.2.4
Summary: Import order detection
Home-page: https://github.com/andymckay/baked
Author: Andy McKay
Author-email: andym@mozilla.com
License: BSD
Platform: UNKNOWN
Classifier: Intended Audience :: Developers
Classifier: Natural Language :: English
Classifier: Operating System :: OS Independent
